tests/__init__.py
tests/test_preprocessing.py
ydne/__init__.py
ydne/preprocessing.py
ydne-0.1.0.dist-info/LICENSE
ydne-0.1.0.dist-info/METADATA
ydne-0.1.0.dist-info/WHEEL
ydne-0.1.0.dist-info/top_level.txt
ydne-0.1.0.dist-info/RECORD
